{
"type": "FeatureCollection",
"name": "P0226-compressor-station",
"crs": { "type": "name", "properties": { "name": "urn:ogc:def:crs:OGC:1.3:CRS84" } },
"features": [
{ "type": "Feature", "properties": { "OBJECTID": 992, "GCOMPID": "GCOMP663", "NAME": "EHRENBERG", "ADDRESS": "50650 COLORADO RIVER ROAD", "CITY": "EHRENBURG", "STATE": "AZ", "ZIP": 85334, "ZIP4": "NOT AVAILABLE", "TYPE": "NATURAL GAS COMPRESSOR STATION", "STATUS": "IN SERVICE", "COUNTY": "LA PAZ", "COUNTYFIPS": 4012, "COUNTRY": "USA", "LATITUDE": 33.59609, "LONGITUDE": -114.530225, "NAICS_CODE": 486210, "NAICS_DESC": "BOOSTER PUMPING STATION, NATURAL GAS TRANSPORTATION", "SOURCE": "EPA ENVIROFACTS, FERC FORM 2, CORPORATE WEBSITE", "SOURCEDATE": "7/15/2020 12:00:00 AM", "VAL_METHOD": "IMAGERY/OTHER", "VAL_DATE": "6/17/2022 12:00:00 AM", "WEBSITE": "https://www.tcenergy.com/operations/natural-gas/north-baja-pipeline-system/", "PIPECO": "NORTH BAJA PIPELINE L.L.C.", "COMPID": 63, "OPERATOR": "NORTH BAJA PIPELINE L.L.C.", "POSREL": "WITHIN 40 FEET", "NUM_UNITS": 2, "CERT_HP": 14500, "PLANT_COST": 53273515, "EXP_FUEL": 1955251, "EXP_OTHER": 451244, "GAS_COMPRE": 616172, "OP_COMP_HR": 12337, "OP_NUM_COM": 2, "OP_DATE_PE": "6/2/2020 12:00:00 AM", "EXP_POWER": 0, "ELEC_COMPR": 0, "x": -12749446.327, "y": 3974694.8716000002 }, "geometry": { "type": "Point", "coordinates": [ -114.530224999136522, 33.596089999969934 ] } }
]
}
