{
"type": "FeatureCollection",
"name": "P0226-compressor-station",
"crs": { "type": "name", "properties": { "name": "urn:ogc:def:crs:EPSG::3857" } },
"features": [
{ "type": "Feature", "properties": { "OBJECTID": 992, "GCOMPID": "GCOMP663", "NAME": "EHRENBERG", "ADDRESS": "50650 COLORADO RIVER ROAD", "CITY": "EHRENBURG", "STATE": "AZ", "ZIP": "85334", "ZIP4": "NOT AVAILABLE", "TYPE": "NATURAL GAS COMPRESSOR STATION", "STATUS": "IN SERVICE", "COUNTY": "LA PAZ", "COUNTYFIPS": "04012", "COUNTRY": "USA", "LATITUDE": 33.59609, "LONGITUDE": -114.530225, "NAICS_CODE": "486210", "NAICS_DESC": "BOOSTER PUMPING STATION, NATURAL GAS TRANSPORTATION", "SOURCE": "EPA ENVIROFACTS, FERC FORM 2, CORPORATE WEBSITE", "SOURCEDATE": "Wed, 15 Jul 2020 00:00:00 GMT", "VAL_METHOD": "IMAGERY/OTHER", "VAL_DATE": "Fri, 17 Jun 2022 00:00:00 GMT", "WEBSITE": "https://www.tcenergy.com/operations/natural-gas/north-baja-pipeline-system/", "PIPECO": "NORTH BAJA PIPELINE L.L.C.", "COMPID": "63", "OPERATOR": "NORTH BAJA PIPELINE L.L.C.", "POSREL": "WITHIN 40 FEET", "NUM_UNITS": 2, "CERT_HP": 14500, "PLANT_COST": 53273515, "EXP_FUEL": 1955251, "EXP_OTHER": 451244, "GAS_COMPRE": 616172, "OP_COMP_HR": 12337, "OP_NUM_COM": 2, "OP_DATE_PE": "Tue, 02 Jun 2020 00:00:00 GMT", "EXP_POWER": 0, "ELEC_COMPR": 0 }, "geometry": { "type": "Point", "coordinates": [ -12749446.327439, 3974694.871639510150999 ] } }
]
}
