
{
    "type": "FeatureCollection",
    "generator": "JOSM",
    "features": [
        {
            "type": "Feature",
            "properties": {
                "CITY": "DEMING",
                "VAL_METHOD": "IMAGERY/OTHER",
                "OBJECTID": "1352",
                "COMPID": "33",
                "EXP_OTHER": "102053",
                "OP_COMP_HR": "0",
                "EXP_POWER": "0",
                "STATE": "NM",
                "NAME": "DEMING",
                "EXP_FUEL": "0",
                "COUNTRY": "USA",
                "WEBSITE": "https://pipeportal.kindermorgan.com/portalui/DefaultKM.aspx?TSP=EPGD",
                "NUM_UNITS": "10",
                "STATUS": "IN SERVICE",
                "OPERATOR": "KINDER MORGAN INC.",
                "GCOMPID": "GCOMP988",
                "CERT_HP": "23100",
                "OP_DATE_PE": "Mon, 14 Mar 2016 00:00:00 GMT",
                "LONGITUDE": "-107.997199531",
                "POSREL": "WITHIN 40 FEET",
                "VAL_DATE": "Fri, 17 Jun 2022 00:00:00 GMT",
                "ADDRESS": "COUNTRY ROAD D006; (13 MI W DEMING, 1 MI N OF I-10)",
                "GAS_COMPRE": "0",
                "ZIP4": "NOT AVAILABLE",
                "SOURCE": "EPA ENVIROFACTS, FERC FORM 2, CORPORATE WEBSITE",
                "COUNTYFIPS": "35029",
                "PIPECO": "EL PASO NATURAL GAS COMPANY L.L.C.",
                "LATITUDE": "32.256878763",
                "ZIP": "88030",
                "COUNTY": "LUNA",
                "NAICS_DESC": "BOOSTER PUMPING STATION, NATURAL GAS TRANSPORTATION",
                "ELEC_COMPR": "0",
                "TYPE": "NATURAL GAS COMPRESSOR STATION",
                "NAICS_CODE": "486210",
                "OP_NUM_COM": "0",
                "PLANT_COST": "-999",
                "SOURCEDATE": "Wed, 15 Jul 2020 00:00:00 GMT"
            },
            "geometry": {
                "type": "Point",
                "coordinates": [
                    -107.99719953100,
                    32.25687876300
                ]
            }
        },
        {
            "type": "Feature",
            "properties": {
                "NUM_UNITS": "2",
                "VAL_METHOD": "IMAGERY/OTHER",
                "COMPID": "33",
                "STATE": "AZ",
                "EXP_POWER": "0",
                "LATITUDE": "32.108861311",
                "NAME": "WILCOX",
                "PLANT_COST": "41068680",
                "OP_COMP_HR": "10676",
                "GCOMPID": "GCOMP1128",
                "COUNTRY": "USA",
                "WEBSITE": "https://pipeportal.kindermorgan.com/portalui/DefaultKM.aspx?TSP=EPGD",
                "ADDRESS": "KANSAS SETTLEMENT; 3 MILES SOUTH OF MP-63 ON I-10",
                "OBJECTID": "144",
                "EXP_FUEL": "891300",
                "CERT_HP": "28000",
                "COUNTYFIPS": "04003",
                "STATUS": "IN SERVICE",
                "OPERATOR": "KINDER MORGAN INC.",
                "LONGITUDE": "-109.662300595",
                "ZIP": "85643",
                "OP_DATE_PE": "Tue, 28 Jul 2020 00:00:00 GMT",
                "COUNTY": "COCHISE",
                "CITY": "WILLCOX",
                "POSREL": "WITHIN 40 FEET",
                "VAL_DATE": "Fri, 17 Jun 2022 00:00:00 GMT",
                "EXP_OTHER": "546609",
                "ZIP4": "NOT AVAILABLE",
                "SOURCE": "EPA ENVIROFACTS, FERC FORM 2, CORPORATE WEBSITE",
                "OP_NUM_COM": "2",
                "PIPECO": "EL PASO NATURAL GAS COMPANY L.L.C.",
                "NAICS_DESC": "BOOSTER PUMPING STATION, NATURAL GAS TRANSPORTATION",
                "ELEC_COMPR": "0",
                "GAS_COMPRE": "676480",
                "TYPE": "NATURAL GAS COMPRESSOR STATION",
                "NAICS_CODE": "486210",
                "SOURCEDATE": "Wed, 15 Jul 2020 00:00:00 GMT"
            },
            "geometry": {
                "type": "Point",
                "coordinates": [
                    -109.66230059500,
                    32.10886131100
                ]
            }
        }
    ]
}